[
  {
    "title": "心理健康与健康的关系",
    "content": "世界卫生组织给健康下的定义为：“健康是一种身体上、精神上和社会适应上的完好状态，而不是没有疾病及虚弱现象。” 全面健康包括躯体健康和心理健康两大部分，两者密切相关，缺一不可，无法分割。这是健康概念的精髓。而现代科学研究表明，30-75%病人的疾病与心理因素有关，生活境遇有关。"
  },
  {
    "title": "心理健康与社会和谐稳定的关系",
    "content": "社会现代化的发展和人口的增加，人际交往日益广泛和复杂，信息的大量增加，竞争日趋激烈，中小学生的学习压力，家长们的家庭及教育压力、购房压力，企业员工及公务员的职场竞争压力，致使心理社会应激增多。和几十年前相比，心理障碍和心理疾病有了成倍的增加。而因为心理疾病引起的社会矛盾事件，社会纠纷越来越多，严重影响了社会的稳定性，影响了社会的和谐发展。"
  },
  {
    "title": "当代人们对心理健康的认知水平",
    "content": "现实生活中，人们对心理健康的认识严重不足，对心理健康知识严重匮乏。不少人认为生理健康和心理健康是两个没有关系的概念。实际上，这是不正确的。在现实生活中，心理健康和生理健康是互相联系、互相作用的，心理健康每时每刻都在影响人的生理健康。"
  }
]